toolgate/__init__.py
toolgate/client.py
toolgate/generated/proto/v1/service_pb2.py
toolgate/generated/proto/v1/service_pb2.pyi
toolgate/langchain/__init__.py
toolgate/langchain/consumers.py
toolgate/langchain/services.py
toolgate/logging.py
toolgate-0.1.2.dist-info/METADATA
toolgate-0.1.2.dist-info/WHEEL
toolgate-0.1.2.dist-info/RECORD
